py_rut.cpython-312-darwin.so
pyrut-0.1.0.dist-info/licenses/LICENSE
pyrut-0.1.0.dist-info/METADATA
pyrut-0.1.0.dist-info/WHEEL
pyrut-0.1.0.dist-info/top_level.txt
pyrut-0.1.0.dist-info/RECORD
