Metadata-Version: 2.4
Name: PyRut
Version: 0.1.0
Summary: High-performance Chilean RUT validation & formatting (Cython)
Home-page: https://github.com/cve-zh00/PyRut
Author: Bastian Garcia
Author-email: bastiang@uc.cl
Classifier: Programming Language :: Python :: 3
Classifier: Programming Language :: Cython
Classifier: License :: OSI Approved :: MIT License
Classifier: Operating System :: OS Independent
Requires-Python: >=3.7
License-File: LICENSE
Dynamic: author
Dynamic: author-email
Dynamic: classifier
Dynamic: description
Dynamic: description-content-type
Dynamic: home-page
Dynamic: license-file
Dynamic: requires-python
Dynamic: summary
